sqlite_utils_sqlite_ulid/__init__.py
sqlite_utils_sqlite_ulid/version.py
sqlite_utils_sqlite_ulid-0.2.1.dist-info/METADATA
sqlite_utils_sqlite_ulid-0.2.1.dist-info/WHEEL
sqlite_utils_sqlite_ulid-0.2.1.dist-info/entry_points.txt
sqlite_utils_sqlite_ulid-0.2.1.dist-info/top_level.txt
sqlite_utils_sqlite_ulid-0.2.1.dist-info/RECORD
